{
  "schema": "incident-snapshot-v1",
  "version_created_at": "2026-04-29T14:15:28-07:00",
  "source_message_id": "<7cdr0X8YSmWoqmj83h6RHQ@geopod-ismtpd-5>",
  "incident": {
    "id": "inc-20260429T141528-platform-change-train-523-northbound-will-depart-from-platfo-7cdr0x8ysmwoqmj83h6rhq-g",
    "title": "Platform change Train 523 Northbound will depart from platform 2 at San Jose Diridon",
    "severity": "minor",
    "status": "investigating",
    "started_at": "2026-04-29T14:14:00-07:00",
    "resolved_at": "2026-04-29T17:22:00-07:00",
    "affected_segments": [
      "Northbound",
      "San Jose Diridon"
    ],
    "summary": "Effect: Modified Service | Cause: Unknown Cause | Location: San Jose Diridon | Start: 04/29/26 2:14 PM | End: 04/29/26 5:22 PM",
    "updates": [
      {
        "timestamp": "2026-04-29T14:15:28-07:00",
        "state": "degraded",
        "message": "Platform change: Train 523 Northbound will depart from platform 2 at\r\n San Jose Diridon. | Effect: Modified Service | Cause: Unknown Cause",
        "source_message_id": "<7cdr0X8YSmWoqmj83h6RHQ@geopod-ismtpd-5>"
      }
    ],
    "ingestion_key": "platform-change-train-523-northbound-will-depart-from-platfo",
    "version_created_at": "2026-04-29T14:15:28-07:00"
  }
}
